manifold_plotter/__init__.py
manifold_plotter-0.0.2.dist-info/LICENSE
manifold_plotter-0.0.2.dist-info/METADATA
manifold_plotter-0.0.2.dist-info/WHEEL
manifold_plotter-0.0.2.dist-info/top_level.txt
manifold_plotter-0.0.2.dist-info/RECORD
